README.md
setup.cfg
setup.py
sheet_sql_report/__init__.py
sheet_sql_report/sheet2sql.py
sheet_sql_report.egg-info/PKG-INFO
sheet_sql_report.egg-info/SOURCES.txt
sheet_sql_report.egg-info/dependency_links.txt
sheet_sql_report.egg-info/not-zip-safe
sheet_sql_report.egg-info/top_level.txt