Metadata-Version: 2.1
Name: sheet-sql-report
Version: 0.1
Summary: Python package to help users connect with google sheet and SQL data
Home-page: https://github.com/jackpegler/sheet-sql-report
Author: Jack Pegler
Author-email: jackpegler@gmail.com
License: UNKNOWN
Platform: UNKNOWN
Classifier: Programming Language :: Python :: 3
Classifier: License :: OSI Approved :: MIT License
Classifier: Operating System :: OS Independent
Requires-Python: >=3.7.4
